pharmcat_runner/__init__.py
pharmcat_runner/__main__.py
pharmcat_runner/common.py
pharmcat_runner/haplotype.py
pharmcat_runner/install.py
pharmcat_runner/parser.py
pharmcat_runner/qc_metrics.py
pharmcat_runner/utils.py
pharmcat_runner/vcf.py
pharmcat_runner/lib/chr_name_conv.txt
pharmcat_runner/lib/cyp2d6_allele_function.json
pharmcat_runner/lib/cyp2d6_cnv_positions.tsv
pharmcat_runner/lib/dip_to_phen.tsv
pharmcat_runner/lib/dpyd_allele_function.json
pharmcat_runner/tests/__init__.py
pharmcat_runner/tests/test_haplotype.py
pharmcat_runner/tests/test_parser.py
pharmcat_runner-0.0.16.dist-info/LICENSE
pharmcat_runner-0.0.16.dist-info/METADATA
pharmcat_runner-0.0.16.dist-info/WHEEL
pharmcat_runner-0.0.16.dist-info/entry_points.txt
pharmcat_runner-0.0.16.dist-info/top_level.txt
pharmcat_runner-0.0.16.dist-info/RECORD
