Metadata-Version: 2.1
Name: pharmcat-runner
Version: 0.0.16
Summary: Installs, runs, and parsers PharmCAT using Pharmacoscan input.
Home-page: UNKNOWN
Author: Andrew Haddad, PharmD
Author-email: andrew.haddad@pitt.edu
License: UNKNOWN
Platform: UNKNOWN
License-File: LICENSE
Requires-Dist: pandas
